toai/__init__.py
toai/imports.py
toai/data/DataContainer.py
toai/data/DataParams.py
toai/data/__init__.py
toai/data/utils.py
toai/encode/CategoricalEncoder.py
toai/encode/__init__.py
toai/extract/Extractor.py
toai/extract/__init__.py
toai/image/ImageAugmentor.py
toai/image/ImageDataset.py
toai/image/ImageLearner.py
toai/image/ImageParser.py
toai/image/ImageResizer.py
toai/image/LearningRateFinder.py
toai/image/__init__.py
toai/inpute/CategoricalInputer.py
toai/inpute/ImageInputer.py
toai/inpute/NumericInputer.py
toai/inpute/__init__.py
toai/metrics/__init__.py
toai/metrics/classification.py
toai/models/__init__.py
toai/models/load_model.py
toai/models/save_model.py
toai/utils/__init__.py
toai/utils/download_file.py
toai_mokahaiku-0.1.0.dist-info/LICENSE
toai_mokahaiku-0.1.0.dist-info/METADATA
toai_mokahaiku-0.1.0.dist-info/WHEEL
toai_mokahaiku-0.1.0.dist-info/top_level.txt
toai_mokahaiku-0.1.0.dist-info/RECORD
